gisaid/__init__.py
gisaid/auth.py
gisaid/exceptions.py
gisaid/helpers.py
gisaid/main.py
gisaid-1.0.5b0.dist-info/LICENSE
gisaid-1.0.5b0.dist-info/METADATA
gisaid-1.0.5b0.dist-info/WHEEL
gisaid-1.0.5b0.dist-info/top_level.txt
gisaid-1.0.5b0.dist-info/RECORD
