Metadata-Version: 2.1
Name: gisaid
Version: 1.0.5b0
Summary: Simplified & efficient GISAID interactions.
Home-page: https://github.com/greysonlalonde/gisaid-uploader
Author: Greyson R. LaLonde
Author-email: greyson.r.lalonde@wmich.edu
License: MIT
Download-URL: https://github.com/greysonlalonde/gisaid-uploader/archive/1.0.5b0.tar.gz
Platform: UNKNOWN
Requires-Dist: pandas
Requires-Dist: numpy
Requires-Dist: biopython
Requires-Dist: requests
